{
"bones": [
	{ "name": "root" },
	{ "name": "torso_top", "parent": "root", "length": 615.15, "x": -118.21, "y": 1344.63, "rotation": 81.49 },
	{
		"name": "arm right",
		"parent": "torso_top",
		"length": 301.82,
		"x": 506.09,
		"y": 182.89,
		"rotation": -161.69,
		"inheritScale": false
	},
	{ "name": "arm_L", "parent": "torso_top", "length": 316.52, "x": 499.33, "y": -165.86, "rotation": -147.88, "inheritScale": false },
	{ "name": "head", "parent": "torso_top", "length": 194.46, "x": 650.63, "y": -47.85, "rotation": -0.9, "inheritScale": false },
	{
		"name": "torso back",
		"parent": "torso_top",
		"length": 609.27,
		"x": 37.94,
		"y": 168.76,
		"rotation": -1.35,
		"inheritScale": false
	},
	{
		"name": "torso front",
		"parent": "torso_top",
		"length": 568.23,
		"x": 29.88,
		"y": -116.06,
		"rotation": -2.25,
		"inheritScale": false
	},
	{
		"name": "torso_bottom",
		"parent": "torso_top",
		"length": 202.06,
		"x": -8.05,
		"y": -1.26,
		"rotation": -90,
		"inheritScale": false,
		"inheritRotation": false
	},
	{
		"name": "bone2",
		"parent": "arm_L",
		"length": 291.16,
		"x": 343.53,
		"y": -1,
		"scaleX": 0.838,
		"rotation": 76.24,
		"inheritScale": false
	},
	{ "name": "bone4", "parent": "arm right", "length": 298.42, "x": 301.79, "y": 0.15, "rotation": 99.38, "inheritScale": false },
	{
		"name": "leg_back",
		"parent": "torso_bottom",
		"length": 540.32,
		"x": 103.24,
		"y": 103.81,
		"rotation": 11.19,
		"inheritScale": false
	},
	{
		"name": "leg_front",
		"parent": "torso_bottom",
		"length": 540.32,
		"x": 95.68,
		"y": -236.47,
		"rotation": 9.9,
		"inheritScale": false
	},
	{
		"name": "bone3",
		"parent": "bone2",
		"length": 77.27,
		"x": 316.35,
		"y": 0.15,
		"scaleX": 0.838,
		"rotation": 69.75,
		"inheritScale": false
	},
	{ "name": "bone5", "parent": "bone4", "length": 81.88, "x": 318.06, "y": -16.86, "rotation": -35.32, "inheritScale": false },
	{ "name": "gun", "parent": "bone4", "length": 437.65, "x": 380.39, "y": -14.4, "rotation": -33.88, "inheritScale": false },
	{ "name": "leg_con_b", "parent": "leg_front", "length": 264.02, "x": 596.9, "y": -23, "rotation": -33.37, "inheritScale": false },
	{ "name": "leg_con_b2", "parent": "leg_back", "length": 264.02, "x": 596.9, "y": -23, "rotation": -33.37, "inheritScale": false },
	{
		"name": "leg_con_t",
		"parent": "leg_front",
		"length": 121.83,
		"x": 544.56,
		"y": -73.25,
		"rotation": -117.64,
		"inheritScale": false
	},
	{
		"name": "leg_con_t2",
		"parent": "leg_back",
		"length": 121.83,
		"x": 544.56,
		"y": -73.25,
		"rotation": -117.64,
		"inheritScale": false
	},
	{ "name": "leg_con_b3", "parent": "leg_con_b2", "length": 264.02, "inheritScale": false },
	{ "name": "leg_con_b4", "parent": "leg_con_b", "length": 264.02, "inheritScale": false },
	{ "name": "leg_m_f", "parent": "leg_con_t", "length": 548.65, "x": 148.13, "y": -8.19, "rotation": 121.69, "inheritScale": false },
	{
		"name": "leg_m_f2",
		"parent": "leg_con_t2",
		"length": 548.65,
		"x": 148.13,
		"y": -8.19,
		"rotation": 121.69,
		"inheritScale": false
	},
	{ "name": "leg_b_f", "parent": "leg_m_f", "length": 157.57, "x": 574.99, "y": -1.84, "rotation": -14.26, "inheritScale": false },
	{ "name": "leg_b_f2", "parent": "leg_m_f2", "length": 157.57, "x": 574.99, "y": -1.84, "rotation": -14.26, "inheritScale": false }
],
"slots": [
	{ "name": "leg_b_b", "bone": "leg_b_f2", "attachment": "warrior 3/leg_b_b" },
	{ "name": "leg_m_b", "bone": "leg_m_f2", "attachment": "warrior 3/leg_m_b" },
	{ "name": "leg_b_f", "bone": "leg_b_f", "attachment": "warrior 3/leg_b_f" },
	{ "name": "leg_con_t_b", "bone": "leg_con_t2", "attachment": "warrior 3/leg_con_t_b" },
	{ "name": "leg_con_b_1_b2", "bone": "leg_con_b2", "attachment": "warrior 3/leg_con_b_1_b" },
	{ "name": "leg_con_b_2_b", "bone": "leg_con_b3", "attachment": "warrior 3/leg_con_b_2_b" },
	{ "name": "leg_m_b_2", "bone": "leg_m_f2", "attachment": "warrior 3/leg_m_b_2" },
	{ "name": "torso_bottom", "bone": "torso_bottom", "attachment": "warrior 3/torso_b" },
	{ "name": "leg_t_b2", "bone": "leg_back", "attachment": "warrior 3/leg_t_b" },
	{ "name": "arm_L_1", "bone": "arm_L", "attachment": "warrior 3/arm_L_1" },
	{ "name": "arm_L_2", "bone": "bone2", "attachment": "warrior 3/arm_L_2" },
	{ "name": "arm_L_3", "bone": "bone3", "attachment": "warrior 3/arm_L_3" },
	{ "name": "torso-1", "bone": "torso front", "attachment": "warrior 3/torso-1" },
	{ "name": "head", "bone": "head", "attachment": "warrior 3/head" },
	{ "name": "torso-2", "bone": "torso back", "attachment": "warrior 3/torso-2" },
	{ "name": "torso-3", "bone": "torso back", "attachment": "warrior 3/torso-3" },
	{ "name": "torso-4", "bone": "torso front", "attachment": "warrior 3/torso-4" },
	{ "name": "torso_top", "bone": "torso_top", "attachment": "warrior 3/torso_t" },
	{ "name": "leg_m_f", "bone": "leg_m_f", "attachment": "warrior 3/leg_m_f" },
	{ "name": "leg_con_b_12", "bone": "leg_con_b", "attachment": "warrior 3/leg_con_b_1" },
	{ "name": "leg_con_b_2_f", "bone": "leg_con_b4", "attachment": "warrior 3/leg_con_b_2_f" },
	{ "name": "leg_con_t", "bone": "leg_con_t", "attachment": "warrior 3/leg_con_t" },
	{ "name": "leg_front", "bone": "leg_front", "attachment": "warrior 3/leg_t_f" },
	{ "name": "leg_m_f_2", "bone": "leg_m_f", "attachment": "warrior 3/leg_m_f_2" },
	{ "name": "gun_pp", "bone": "gun", "attachment": "warrior 3/gun_pp" },
	{ "name": "gun_pp_bolt", "bone": "gun", "attachment": "warrior 3/gun_pp_bolt" },
	{ "name": "arm_r_1", "bone": "arm right", "attachment": "warrior 3/arm_r_1" },
	{ "name": "arm_r_3", "bone": "bone5", "attachment": "warrior 3/arm_r_3" },
	{ "name": "arm_r_2", "bone": "bone4", "attachment": "warrior 3/arm_r_2" },
	{ "name": "muzzle-flash-1", "bone": "gun", "color": "ffffff00", "attachment": "warrior sprites/muzzle-flash-1" },
	{ "name": "muzzle-flash-2", "bone": "gun", "color": "ffffff00", "attachment": "warrior sprites/muzzle-flash-2" },
	{ "name": "muzzle-flash-3", "bone": "gun", "color": "ffffff00", "attachment": "warrior sprites/muzzle-flash-3" }
],
"skins": {
	"default": {
		"arm_L_1": {
			"warrior 3/arm_L_1": { "x": 143.44, "y": -2.82, "rotation": 2.25, "width": 408, "height": 188 }
		},
		"arm_L_2": {
			"warrior 3/arm_L_2": { "x": 135.21, "y": 15.05, "rotation": 1.35, "width": 452, "height": 159 }
		},
		"arm_L_3": {
			"warrior 3/arm_L_3": { "x": 44.24, "y": 5.13, "rotation": 0.45, "width": 177, "height": 152 }
		},
		"arm_r_1": {
			"warrior 3/arm_r_1": { "x": 160.63, "y": -6.47, "rotation": 80.2, "width": 242, "height": 428 }
		},
		"arm_r_2": {
			"warrior 3/arm_r_2": { "x": 133.09, "y": -48.08, "rotation": -19.18, "width": 466, "height": 252 }
		},
		"arm_r_3": {
			"warrior 3/arm_r_3": { "x": 40.99, "y": -13.1, "rotation": 16.13, "width": 203, "height": 148 }
		},
		"gun_pp": {
			"warrior 3/gun_pp": { "x": 143.94, "y": 6.02, "rotation": -0.27, "width": 785, "height": 438 }
		},
		"gun_pp_bolt": {
			"warrior 3/gun_pp_bolt": { "x": -84.78, "y": 85.64, "rotation": -0.06, "width": 119, "height": 21 }
		},
		"head": {
			"warrior 3/head": { "x": 156.83, "y": -9.8, "rotation": -79.85, "width": 624, "height": 543 }
		},
		"leg_b_b": {
			"warrior 3/leg_b_b": { "x": 51.4, "y": 15.42, "rotation": 90.31, "width": 424, "height": 296 }
		},
		"leg_b_f": {
			"warrior 3/leg_b_f": { "x": 54.96, "y": 12.31, "rotation": 90.31, "width": 424, "height": 296 }
		},
		"leg_con_b_12": {
			"warrior 3/leg_con_b_1": { "x": 136.31, "y": -4.32, "rotation": 90.42, "width": 58, "height": 255 }
		},
		"leg_con_b_1_b2": {
			"warrior 3/leg_con_b_1_b": { "x": 133.99, "y": -5.81, "rotation": 89.48, "width": 58, "height": 255 }
		},
		"leg_con_b_2_b": {
			"warrior 3/leg_con_b_2_b": { "x": 116.24, "y": -14.49, "rotation": 88.81, "width": 114, "height": 210 }
		},
		"leg_con_b_2_f": {
			"warrior 3/leg_con_b_2_f": { "x": 116.33, "y": -13.98, "rotation": 88.65, "width": 114, "height": 210 }
		},
		"leg_con_t": {
			"warrior 3/leg_con_t": { "x": 53.87, "y": -5.69, "rotation": -179.58, "width": 139, "height": 59 }
		},
		"leg_con_t_b": {
			"warrior 3/leg_con_t_b": { "x": 54.42, "y": -6.06, "rotation": -179.2, "width": 139, "height": 59 }
		},
		"leg_front": {
			"warrior 3/leg_t_f": { "x": 290.46, "y": 46.87, "rotation": 80.09, "width": 408, "height": 747 }
		},
		"leg_m_b": {
			"warrior 3/leg_m_b": { "x": 260.58, "y": 6.22, "rotation": 76.04, "width": 352, "height": 681 }
		},
		"leg_m_b_2": {
			"warrior 3/leg_m_b_2": { "x": 302.38, "y": -49.01, "rotation": 76.04, "width": 187, "height": 323 }
		},
		"leg_m_f": {
			"warrior 3/leg_m_f": { "x": 262.38, "y": 6.89, "rotation": 76.04, "width": 352, "height": 681 }
		},
		"leg_m_f_2": {
			"warrior 3/leg_m_f_2": { "x": 305.17, "y": -48.78, "rotation": 76.04, "width": 187, "height": 325 }
		},
		"leg_t_b2": {
			"warrior 3/leg_t_b": { "x": 290.82, "y": 43.61, "rotation": 80.09, "width": 408, "height": 747 }
		},
		"muzzle-flash-1": {
			"warrior sprites/muzzle-flash-1": { "x": 721.43, "y": 46.22, "rotation": 0.59, "width": 409, "height": 229 }
		},
		"muzzle-flash-2": {
			"warrior sprites/muzzle-flash-2": { "x": 866.46, "y": 43.16, "rotation": 0.76, "width": 859, "height": 638 }
		},
		"muzzle-flash-3": {
			"warrior sprites/muzzle-flash-3": { "x": 840.88, "y": 50.79, "rotation": 3.6, "width": 676, "height": 580 }
		},
		"torso-1": {
			"warrior 3/torso-1": { "x": 406.73, "y": 53.83, "rotation": -79.23, "width": 455, "height": 555 }
		},
		"torso-2": {
			"warrior 3/torso-2": { "x": 393.61, "y": -61.8, "rotation": -80.13, "width": 514, "height": 544 }
		},
		"torso-3": {
			"warrior 3/torso-3": { "x": 100.17, "y": 85.04, "rotation": -80.13, "width": 340, "height": 307 }
		},
		"torso-4": {
			"warrior 3/torso-4": { "x": 85.79, "y": 27.07, "rotation": -79.23, "width": 421, "height": 210 }
		},
		"torso_bottom": {
			"warrior 3/torso_b": { "x": 69.35, "y": -39.79, "rotation": 90, "width": 513, "height": 414 }
		},
		"torso_top": {
			"warrior 3/torso_t": { "x": 352.41, "y": 61.82, "rotation": -81.49, "width": 779, "height": 717 }
		}
	}
},
"animations": {
	"Battle stance": {
		"bones": {
			"torso_top": {
				"rotate": [
					{ "time": 0, "angle": -3.1, "curve": "stepped" },
					{ "time": 1, "angle": -3.1 }
				],
				"translate": [
					{ "time": 0, "x": -18.36, "y": -122.65 },
					{ "time": 0.5, "x": -18.36, "y": -137.52 },
					{ "time": 1, "x": -18.36, "y": -122.65 }
				]
			},
			"leg_back": {
				"rotate": [
					{ "time": 0, "angle": 24.95, "curve": "stepped" },
					{ "time": 1, "angle": 24.95 }
				]
			},
			"leg_con_t2": {
				"rotate": [
					{ "time": 0, "angle": -41.28 },
					{ "time": 0.5, "angle": -48.35 },
					{ "time": 1, "angle": -41.28 }
				]
			},
			"leg_m_f2": {
				"rotate": [
					{ "time": 0, "angle": 22 },
					{ "time": 0.5, "angle": 27.64 },
					{ "time": 1, "angle": 22 }
				]
			},
			"leg_b_f2": {
				"rotate": [
					{ "time": 0, "angle": -6.43 },
					{ "time": 0.5, "angle": -4.52 },
					{ "time": 1, "angle": -6.43 }
				]
			},
			"leg_con_b2": {
				"rotate": [
					{ "time": 0, "angle": -1.83, "curve": "stepped" },
					{ "time": 1, "angle": -1.83 }
				],
				"scale": [
					{ "time": 0, "x": 1.346, "y": 1, "curve": "stepped" },
					{ "time": 1, "x": 1.346, "y": 1 }
				]
			},
			"leg_front": {
				"rotate": [
					{ "time": 0, "angle": 4.85 },
					{ "time": 0.5, "angle": 5.66 },
					{ "time": 1, "angle": 4.85 }
				]
			},
			"leg_m_f": {
				"rotate": [
					{ "time": 0, "angle": -19.64 },
					{ "time": 0.5, "angle": -17.63 },
					{ "time": 1, "angle": -19.64 }
				]
			},
			"leg_con_t": {
				"rotate": [
					{ "time": 0, "angle": -28.23 },
					{ "time": 0.5, "angle": -32.6 },
					{ "time": 1, "angle": -28.23 }
				]
			},
			"leg_b_f": {
				"rotate": [
					{ "time": 0, "angle": 43.4 },
					{ "time": 0.5, "angle": 44.38 },
					{ "time": 1, "angle": 43.4 }
				]
			},
			"leg_con_b": {
				"rotate": [
					{ "time": 0, "angle": -48.65 },
					{ "time": 0.5, "angle": -50.89 },
					{ "time": 1, "angle": -48.65 }
				],
				"scale": [
					{ "time": 0, "x": 1.308, "y": 1, "curve": "stepped" },
					{ "time": 1, "x": 1.308, "y": 1 }
				]
			},
			"head": {
				"rotate": [
					{ "time": 0, "angle": 7.96, "curve": "stepped" },
					{ "time": 1, "angle": 7.96 }
				]
			},
			"arm right": {
				"rotate": [
					{ "time": 0, "angle": 23.45 },
					{ "time": 0.5, "angle": 21.93 },
					{ "time": 1, "angle": 23.45 }
				]
			},
			"bone4": {
				"rotate": [
					{ "time": 0, "angle": -11.3, "curve": "stepped" },
					{ "time": 1, "angle": -11.3 }
				]
			},
			"gun": {
				"rotate": [
					{ "time": 0, "angle": 1.33 },
					{ "time": 0.5, "angle": 3.15 },
					{ "time": 1, "angle": 1.33 }
				]
			},
			"arm_L": {
				"rotate": [
					{ "time": 0, "angle": 28.44 },
					{ "time": 0.5, "angle": 26.56 },
					{ "time": 1, "angle": 28.44 }
				]
			},
			"bone3": {
				"rotate": [
					{ "time": 0, "angle": -53.58, "curve": "stepped" },
					{ "time": 1, "angle": -53.58 }
				]
			}
		}
	},
	"Shooting": {
		"bones": {
			"torso_top": {
				"rotate": [
					{ "time": 0, "angle": -3.1, "curve": "stepped" },
					{
						"time": 0.0333,
						"angle": -3.1,
						"curve": [ 0.328, 0.33, 0.661, 0.66 ]
					},
					{
						"time": 0.1,
						"angle": -2.2,
						"curve": [ 0.328, 0.33, 0.661, 0.66 ]
					},
					{
						"time": 0.1666,
						"angle": -2.24,
						"curve": [ 0.328, 0.33, 0.661, 0.66 ]
					},
					{
						"time": 0.2333,
						"angle": -1.73,
						"curve": [ 0.328, 0.33, 0.661, 0.66 ]
					},
					{
						"time": 0.3,
						"angle": -1.9,
						"curve": [ 0.328, 0.33, 0.662, 0.66 ]
					},
					{
						"time": 0.3666,
						"angle": -1.37,
						"curve": [ 0.328, 0.33, 0.662, 0.66 ]
					},
					{
						"time": 0.4333,
						"angle": -1.5,
						"curve": [ 0.328, 0.33, 0.662, 0.66 ]
					},
					{
						"time": 0.5,
						"angle": -0.78,
						"curve": [ 0.329, 0.33, 0.662, 0.66 ]
					},
					{
						"time": 0.5666,
						"angle": -1.15,
						"curve": [ 0.329, 0.33, 0.662, 0.66 ]
					},
					{
						"time": 0.6333,
						"angle": -0.22,
						"curve": [ 0.329, 0.33, 0.662, 0.66 ]
					},
					{ "time": 0.7, "angle": -0.62 },
					{ "time": 0.8, "angle": -3.1 },
					{ "time": 0.9333, "angle": -4.08 },
					{ "time": 1.1333, "angle": -3.1 }
				],
				"translate": [
					{ "time": 0, "x": -18.36, "y": -122.65, "curve": "stepped" },
					{ "time": 0.0333, "x": -18.36, "y": -122.65 },
					{ "time": 0.7, "x": -30.99, "y": -120.43 },
					{ "time": 0.8, "x": -18.36, "y": -122.65 },
					{ "time": 0.9333, "x": -13.6, "y": -122.65 },
					{ "time": 1.1333, "x": -18.36, "y": -122.65 }
				],
				"scale": [
					{ "time": 0, "x": 1, "y": 1, "curve": "stepped" },
					{ "time": 0.0333, "x": 1, "y": 1 },
					{ "time": 0.1, "x": 1, "y": 1.02 },
					{ "time": 0.1666, "x": 1, "y": 1 },
					{ "time": 0.2333, "x": 1, "y": 1.02 },
					{ "time": 0.3, "x": 1, "y": 1 },
					{ "time": 0.3666, "x": 1, "y": 1.02 },
					{ "time": 0.4333, "x": 1, "y": 1 },
					{ "time": 0.5, "x": 1, "y": 1.02 },
					{ "time": 0.5666, "x": 1, "y": 1 },
					{ "time": 0.6333, "x": 1, "y": 1.02 },
					{ "time": 0.7, "x": 1, "y": 1, "curve": "stepped" },
					{ "time": 0.8, "x": 1, "y": 1, "curve": "stepped" },
					{ "time": 1.1333, "x": 1, "y": 1 }
				]
			},
			"leg_back": {
				"rotate": [
					{ "time": 0, "angle": 24.95, "curve": "stepped" },
					{ "time": 0.0333, "angle": 24.95, "curve": "stepped" },
					{ "time": 0.8, "angle": 24.95, "curve": "stepped" },
					{ "time": 1.0333, "angle": 24.95 }
				]
			},
			"leg_con_t2": {
				"rotate": [
					{ "time": 0, "angle": -41.28, "curve": "stepped" },
					{ "time": 0.0333, "angle": -41.28 },
					{ "time": 0.7, "angle": -37.23 },
					{ "time": 0.8, "angle": -41.28, "curve": "stepped" },
					{ "time": 1.0333, "angle": -41.28 }
				]
			},
			"leg_m_f2": {
				"rotate": [
					{ "time": 0, "angle": 22, "curve": "stepped" },
					{ "time": 0.0333, "angle": 22 },
					{ "time": 0.7, "angle": 20 },
					{ "time": 0.8, "angle": 22 },
					{ "time": 0.9333, "angle": 21.83 },
					{ "time": 1.0333, "angle": 22 }
				]
			},
			"leg_b_f2": {
				"rotate": [
					{ "time": 0, "angle": -6.43, "curve": "stepped" },
					{ "time": 0.0333, "angle": -6.43 },
					{ "time": 0.7, "angle": -9.13 },
					{ "time": 0.8, "angle": -6.43, "curve": "stepped" },
					{ "time": 1.0333, "angle": -6.43 }
				]
			},
			"leg_con_b2": {
				"rotate": [
					{ "time": 0, "angle": -1.83, "curve": "stepped" },
					{ "time": 0.0333, "angle": -1.83 },
					{ "time": 0.7, "angle": 0.31 },
					{ "time": 0.8, "angle": -1.83, "curve": "stepped" },
					{ "time": 1.0333, "angle": -1.83 }
				],
				"scale": [
					{ "time": 0, "x": 1.346, "y": 1, "curve": "stepped" },
					{ "time": 0.0333, "x": 1.346, "y": 1, "curve": "stepped" },
					{ "time": 0.8, "x": 1.346, "y": 1, "curve": "stepped" },
					{ "time": 1.0333, "x": 1.346, "y": 1 }
				]
			},
			"leg_front": {
				"rotate": [
					{ "time": 0, "angle": 4.85, "curve": "stepped" },
					{ "time": 0.0333, "angle": 4.85 },
					{ "time": 0.7, "angle": 5.4 },
					{ "time": 0.8, "angle": 4.85, "curve": "stepped" },
					{ "time": 1.0333, "angle": 4.85 }
				]
			},
			"leg_m_f": {
				"rotate": [
					{ "time": 0, "angle": -19.64, "curve": "stepped" },
					{ "time": 0.0333, "angle": -19.64 },
					{ "time": 0.7, "angle": -19.45 },
					{ "time": 0.8, "angle": -19.64 },
					{ "time": 0.9333, "angle": -19.73 },
					{ "time": 1.0333, "angle": -19.64 }
				]
			},
			"leg_con_t": {
				"rotate": [
					{ "time": 0, "angle": -28.23, "curve": "stepped" },
					{ "time": 0.0333, "angle": -28.23 },
					{ "time": 0.7, "angle": -28.25 },
					{ "time": 0.8, "angle": -28.23, "curve": "stepped" },
					{ "time": 1.0333, "angle": -28.23 }
				]
			},
			"leg_b_f": {
				"rotate": [
					{ "time": 0, "angle": 43.4, "curve": "stepped" },
					{ "time": 0.0333, "angle": 43.4 },
					{ "time": 0.7, "angle": 42.56 },
					{ "time": 0.8, "angle": 43.4, "curve": "stepped" },
					{ "time": 1.0333, "angle": 43.4 }
				]
			},
			"leg_con_b": {
				"rotate": [
					{ "time": 0, "angle": -48.65, "curve": "stepped" },
					{ "time": 0.0333, "angle": -48.65, "curve": "stepped" },
					{ "time": 0.7, "angle": -48.65, "curve": "stepped" },
					{ "time": 0.8, "angle": -48.65, "curve": "stepped" },
					{ "time": 1.0333, "angle": -48.65 }
				],
				"scale": [
					{ "time": 0, "x": 1.308, "y": 1, "curve": "stepped" },
					{ "time": 0.0333, "x": 1.308, "y": 1, "curve": "stepped" },
					{ "time": 0.7, "x": 1.308, "y": 1, "curve": "stepped" },
					{ "time": 0.8, "x": 1.308, "y": 1, "curve": "stepped" },
					{ "time": 1.0333, "x": 1.308, "y": 1 }
				]
			},
			"head": {
				"rotate": [
					{ "time": 0, "angle": 7.96, "curve": "stepped" },
					{ "time": 0.0333, "angle": 7.96, "curve": "stepped" },
					{ "time": 0.1666, "angle": 7.96, "curve": "stepped" },
					{ "time": 0.3, "angle": 7.96, "curve": "stepped" },
					{ "time": 0.4333, "angle": 7.96, "curve": "stepped" },
					{ "time": 0.5666, "angle": 7.96, "curve": "stepped" },
					{ "time": 0.8, "angle": 7.96, "curve": "stepped" },
					{ "time": 1.0333, "angle": 7.96 }
				]
			},
			"arm right": {
				"rotate": [
					{ "time": 0, "angle": 23.45, "curve": "stepped" },
					{ "time": 0.0333, "angle": 23.45, "curve": "stepped" },
					{ "time": 0.1666, "angle": 23.45, "curve": "stepped" },
					{ "time": 0.3, "angle": 23.45, "curve": "stepped" },
					{ "time": 0.4333, "angle": 23.45, "curve": "stepped" },
					{ "time": 0.5666, "angle": 23.45, "curve": "stepped" },
					{ "time": 0.7, "angle": 23.45, "curve": "stepped" },
					{ "time": 0.8, "angle": 23.45, "curve": "stepped" },
					{ "time": 1.0333, "angle": 23.45 }
				],
				"translate": [
					{ "time": 0, "x": 0, "y": 0, "curve": "stepped" },
					{ "time": 0.0333, "x": 0, "y": 0, "curve": "stepped" },
					{ "time": 0.1666, "x": 0, "y": 0, "curve": "stepped" },
					{ "time": 0.3, "x": 0, "y": 0, "curve": "stepped" },
					{ "time": 0.4333, "x": 0, "y": 0, "curve": "stepped" },
					{ "time": 0.5666, "x": 0, "y": 0, "curve": "stepped" },
					{ "time": 0.7, "x": 0, "y": 0, "curve": "stepped" },
					{ "time": 0.8, "x": 0, "y": 0, "curve": "stepped" },
					{ "time": 1.0333, "x": 0, "y": 0 }
				]
			},
			"bone4": {
				"rotate": [
					{ "time": 0, "angle": -11.3, "curve": "stepped" },
					{ "time": 0.0333, "angle": -11.3 },
					{ "time": 0.1, "angle": -10.91 },
					{ "time": 0.1666, "angle": -11.3 },
					{ "time": 0.2333, "angle": -10.91 },
					{ "time": 0.3, "angle": -11.3 },
					{ "time": 0.3666, "angle": -10.91 },
					{ "time": 0.4333, "angle": -11.3 },
					{ "time": 0.5, "angle": -10.91 },
					{ "time": 0.5666, "angle": -11.3 },
					{ "time": 0.6333, "angle": -10.91 },
					{ "time": 0.7, "angle": -11.3, "curve": "stepped" },
					{ "time": 0.8, "angle": -11.3, "curve": "stepped" },
					{ "time": 1.0333, "angle": -11.3 }
				],
				"translate": [
					{ "time": 0, "x": 0, "y": 0, "curve": "stepped" },
					{ "time": 0.0333, "x": 0, "y": 0, "curve": "stepped" },
					{ "time": 0.1666, "x": 0, "y": 0, "curve": "stepped" },
					{ "time": 0.3, "x": 0, "y": 0, "curve": "stepped" },
					{ "time": 0.4333, "x": 0, "y": 0, "curve": "stepped" },
					{ "time": 0.5666, "x": 0, "y": 0, "curve": "stepped" },
					{ "time": 0.7, "x": 0, "y": 0, "curve": "stepped" },
					{ "time": 0.8, "x": 0, "y": 0, "curve": "stepped" },
					{ "time": 1.0333, "x": 0, "y": 0 }
				]
			},
			"gun": {
				"rotate": [
					{ "time": 0, "angle": 1.33, "curve": "stepped" },
					{ "time": 0.0333, "angle": 1.33 },
					{ "time": 0.1, "angle": 1.81 },
					{ "time": 0.1666, "angle": 1.33 },
					{ "time": 0.2333, "angle": 1.81 },
					{ "time": 0.3, "angle": 1.33 },
					{ "time": 0.3666, "angle": 1.81 },
					{ "time": 0.4333, "angle": 1.33 },
					{ "time": 0.5, "angle": 1.81 },
					{ "time": 0.5666, "angle": 1.33 },
					{ "time": 0.6333, "angle": 1.81 },
					{ "time": 0.7, "angle": 1.33, "curve": "stepped" },
					{ "time": 0.8, "angle": 1.33, "curve": "stepped" },
					{ "time": 1.0333, "angle": 1.33 }
				],
				"translate": [
					{ "time": 0, "x": 0, "y": 0, "curve": "stepped" },
					{ "time": 0.0333, "x": 0, "y": 0, "curve": "stepped" },
					{ "time": 0.1666, "x": 0, "y": 0, "curve": "stepped" },
					{ "time": 0.3, "x": 0, "y": 0, "curve": "stepped" },
					{ "time": 0.4333, "x": 0, "y": 0, "curve": "stepped" },
					{ "time": 0.5666, "x": 0, "y": 0, "curve": "stepped" },
					{ "time": 0.7, "x": 0, "y": 0, "curve": "stepped" },
					{ "time": 0.8, "x": 0, "y": 0, "curve": "stepped" },
					{ "time": 1.0333, "x": 0, "y": 0 }
				]
			},
			"arm_L": {
				"rotate": [
					{ "time": 0, "angle": 28.44, "curve": "stepped" },
					{ "time": 0.0333, "angle": 28.44 },
					{ "time": 0.1, "angle": 28.37 },
					{ "time": 0.1666, "angle": 28.44 },
					{ "time": 0.2333, "angle": 27.42 },
					{ "time": 0.3, "angle": 28.44 },
					{ "time": 0.3666, "angle": 27.42 },
					{ "time": 0.4333, "angle": 28.44 },
					{ "time": 0.5, "angle": 27.42 },
					{ "time": 0.5666, "angle": 28.44 },
					{ "time": 0.6333, "angle": 27.42 },
					{ "time": 0.7, "angle": 28.44, "curve": "stepped" },
					{ "time": 0.8, "angle": 28.44, "curve": "stepped" },
					{ "time": 1.0333, "angle": 28.44 }
				],
				"translate": [
					{ "time": 0, "x": 0, "y": 0, "curve": "stepped" },
					{ "time": 0.0333, "x": 0, "y": 0, "curve": "stepped" },
					{ "time": 0.1666, "x": 0, "y": 0, "curve": "stepped" },
					{ "time": 0.3, "x": 0, "y": 0, "curve": "stepped" },
					{ "time": 0.4333, "x": 0, "y": 0, "curve": "stepped" },
					{ "time": 0.5666, "x": 0, "y": 0, "curve": "stepped" },
					{ "time": 0.7, "x": 0, "y": 0, "curve": "stepped" },
					{ "time": 0.8, "x": 0, "y": 0, "curve": "stepped" },
					{ "time": 1.0333, "x": 0, "y": 0 }
				]
			},
			"bone3": {
				"rotate": [
					{ "time": 0, "angle": -53.58, "curve": "stepped" },
					{ "time": 0.0333, "angle": -53.58 },
					{ "time": 0.1, "angle": -53.68 },
					{ "time": 0.1666, "angle": -53.58 },
					{ "time": 0.2333, "angle": -53.68 },
					{ "time": 0.3, "angle": -53.58 },
					{ "time": 0.3666, "angle": -53.68 },
					{ "time": 0.4333, "angle": -53.58 },
					{ "time": 0.5, "angle": -53.68 },
					{ "time": 0.5666, "angle": -53.58 },
					{ "time": 0.6333, "angle": -53.68 },
					{ "time": 0.7, "angle": -53.58, "curve": "stepped" },
					{ "time": 0.8, "angle": -53.58, "curve": "stepped" },
					{ "time": 1.0333, "angle": -53.58 }
				],
				"translate": [
					{ "time": 0, "x": 0, "y": 0, "curve": "stepped" },
					{ "time": 0.0333, "x": 0, "y": 0, "curve": "stepped" },
					{ "time": 0.1666, "x": 0, "y": 0, "curve": "stepped" },
					{ "time": 0.3, "x": 0, "y": 0, "curve": "stepped" },
					{ "time": 0.4333, "x": 0, "y": 0, "curve": "stepped" },
					{ "time": 0.5666, "x": 0, "y": 0, "curve": "stepped" },
					{ "time": 0.7, "x": 0, "y": 0, "curve": "stepped" },
					{ "time": 0.8, "x": 0, "y": 0, "curve": "stepped" },
					{ "time": 1.0333, "x": 0, "y": 0 }
				]
			},
			"torso back": {
				"scale": [
					{ "time": 0, "x": 1, "y": 1, "curve": "stepped" },
					{ "time": 0.0333, "x": 1, "y": 1 },
					{ "time": 0.1, "x": 1, "y": 0.97 },
					{ "time": 0.1666, "x": 1, "y": 1 },
					{ "time": 0.2333, "x": 1, "y": 0.97 },
					{ "time": 0.3, "x": 1, "y": 1 },
					{ "time": 0.3666, "x": 1, "y": 0.97 },
					{ "time": 0.4333, "x": 1, "y": 1 },
					{ "time": 0.5, "x": 1, "y": 0.97 },
					{ "time": 0.5666, "x": 1, "y": 1 },
					{ "time": 0.6333, "x": 1, "y": 0.97 },
					{ "time": 0.7, "x": 1, "y": 1, "curve": "stepped" },
					{ "time": 0.8, "x": 1, "y": 1, "curve": "stepped" },
					{ "time": 1.0333, "x": 1, "y": 1 }
				]
			},
			"torso front": {
				"scale": [
					{ "time": 0, "x": 1, "y": 1, "curve": "stepped" },
					{ "time": 0.0333, "x": 1, "y": 1 },
					{ "time": 0.1, "x": 1, "y": 1.02 },
					{ "time": 0.1666, "x": 1, "y": 1 },
					{ "time": 0.2333, "x": 1, "y": 1.02 },
					{ "time": 0.3, "x": 1, "y": 1 },
					{ "time": 0.3666, "x": 1, "y": 1.02 },
					{ "time": 0.4333, "x": 1, "y": 1 },
					{ "time": 0.5, "x": 1, "y": 1.02 },
					{ "time": 0.5666, "x": 1, "y": 1 },
					{ "time": 0.6333, "x": 1, "y": 1.02 },
					{ "time": 0.7, "x": 1, "y": 1, "curve": "stepped" },
					{ "time": 0.8, "x": 1, "y": 1, "curve": "stepped" },
					{ "time": 1.0333, "x": 1, "y": 1 }
				]
			},
			"bone5": {
				"rotate": [
					{ "time": 0, "angle": 0, "curve": "stepped" },
					{ "time": 0.0333, "angle": 0, "curve": "stepped" },
					{ "time": 0.1666, "angle": 0, "curve": "stepped" },
					{ "time": 0.3, "angle": 0, "curve": "stepped" },
					{ "time": 0.4333, "angle": 0, "curve": "stepped" },
					{ "time": 0.5666, "angle": 0, "curve": "stepped" },
					{ "time": 0.7, "angle": 0, "curve": "stepped" },
					{ "time": 0.8, "angle": 0, "curve": "stepped" },
					{ "time": 1.0333, "angle": 0 }
				],
				"translate": [
					{ "time": 0, "x": 0, "y": 0, "curve": "stepped" },
					{ "time": 0.0333, "x": 0, "y": 0, "curve": "stepped" },
					{ "time": 0.1666, "x": 0, "y": 0, "curve": "stepped" },
					{ "time": 0.3, "x": 0, "y": 0, "curve": "stepped" },
					{ "time": 0.4333, "x": 0, "y": 0, "curve": "stepped" },
					{ "time": 0.5666, "x": 0, "y": 0, "curve": "stepped" },
					{ "time": 0.7, "x": 0, "y": 0, "curve": "stepped" },
					{ "time": 0.8, "x": 0, "y": 0, "curve": "stepped" },
					{ "time": 1.0333, "x": 0, "y": 0 }
				]
			},
			"bone2": {
				"rotate": [
					{ "time": 0, "angle": 0, "curve": "stepped" },
					{ "time": 0.0333, "angle": 0 },
					{ "time": 0.1, "angle": 3.17 },
					{ "time": 0.1666, "angle": 0 },
					{ "time": 0.2333, "angle": 3.17 },
					{ "time": 0.3, "angle": 0 },
					{ "time": 0.3666, "angle": 3.17 },
					{ "time": 0.4333, "angle": 0 },
					{ "time": 0.5, "angle": 3.17 },
					{ "time": 0.5666, "angle": 0 },
					{ "time": 0.6333, "angle": 3.17 },
					{ "time": 0.7, "angle": 0, "curve": "stepped" },
					{ "time": 0.8, "angle": 0, "curve": "stepped" },
					{ "time": 1.0333, "angle": 0 }
				],
				"translate": [
					{ "time": 0, "x": 0, "y": 0, "curve": "stepped" },
					{ "time": 0.0333, "x": 0, "y": 0, "curve": "stepped" },
					{ "time": 0.1666, "x": 0, "y": 0, "curve": "stepped" },
					{ "time": 0.3, "x": 0, "y": 0, "curve": "stepped" },
					{ "time": 0.4333, "x": 0, "y": 0, "curve": "stepped" },
					{ "time": 0.5666, "x": 0, "y": 0, "curve": "stepped" },
					{ "time": 0.7, "x": 0, "y": 0, "curve": "stepped" },
					{ "time": 0.8, "x": 0, "y": 0, "curve": "stepped" },
					{ "time": 1.0333, "x": 0, "y": 0 }
				]
			}
		},
		"slots": {
			"gun_pp_bolt": {
				"color": [
					{ "time": 0.0333, "color": "ffffffff" },
					{ "time": 0.1, "color": "ffffff00" },
					{ "time": 0.1666, "color": "ffffffff" },
					{ "time": 0.2333, "color": "ffffff00" },
					{ "time": 0.3, "color": "ffffffff" },
					{ "time": 0.3666, "color": "ffffff00" },
					{ "time": 0.4333, "color": "ffffffff" },
					{ "time": 0.5, "color": "ffffff00" },
					{ "time": 0.5666, "color": "ffffffff" },
					{ "time": 0.6333, "color": "ffffff00" },
					{ "time": 0.7, "color": "ffffffff" }
				]
			},
			"muzzle-flash-1": {
				"color": [
					{ "time": 0.0333, "color": "ffffff00" },
					{ "time": 0.1, "color": "ffffffff" },
					{ "time": 0.1666, "color": "ffffff00", "curve": "stepped" },
					{ "time": 0.4333, "color": "ffffff00" },
					{ "time": 0.5, "color": "ffffffff" },
					{ "time": 0.5666, "color": "ffffff00" }
				]
			},
			"muzzle-flash-2": {
				"color": [
					{ "time": 0.1666, "color": "ffffff00" },
					{ "time": 0.2333, "color": "ffffffff" },
					{ "time": 0.3, "color": "ffffff00", "curve": "stepped" },
					{ "time": 0.5666, "color": "ffffff00" },
					{ "time": 0.6333, "color": "ffffffff" },
					{ "time": 0.7, "color": "ffffff00" }
				]
			},
			"muzzle-flash-3": {
				"color": [
					{ "time": 0.3, "color": "ffffff00" },
					{ "time": 0.3666, "color": "ffffffff" },
					{ "time": 0.4333, "color": "ffffff00" }
				]
			}
		}
	},
	"Walking": {
		"bones": {
			"leg_front": {
				"rotate": [
					{ "time": 0, "angle": -26.34 },
					{ "time": 0.1, "angle": -14.5 },
					{ "time": 0.2, "angle": 23.31 },
					{ "time": 0.3, "angle": 41.93 },
					{ "time": 0.4, "angle": 31.44 },
					{ "time": 0.5, "angle": 23.96 },
					{ "time": 0.6, "angle": 14.26 },
					{ "time": 0.64, "angle": 8.39 },
					{ "time": 0.8, "angle": -26.34 }
				],
				"translate": [
					{ "time": 0, "x": 0, "y": 0, "curve": "stepped" },
					{ "time": 0.8, "x": 0, "y": 0 }
				]
			},
			"leg_b_f": {
				"rotate": [
					{ "time": 0, "angle": 26.87 },
					{ "time": 0.1, "angle": 29.73 },
					{ "time": 0.2, "angle": 36.51 },
					{ "time": 0.3, "angle": -15.44 },
					{ "time": 0.4, "angle": -6.21 },
					{ "time": 0.5, "angle": -8.77 },
					{ "time": 0.6, "angle": -9.63 },
					{ "time": 0.64, "angle": -6.87 },
					{ "time": 0.8, "angle": 26.87 }
				],
				"translate": [
					{ "time": 0, "x": 0, "y": 0, "curve": "stepped" },
					{ "time": 0.8, "x": 0, "y": 0 }
				]
			},
			"leg_m_f": {
				"rotate": [
					{ "time": 0, "angle": -19.88 },
					{ "time": 0.1, "angle": -23.49 },
					{ "time": 0.2, "angle": -42.57 },
					{ "time": 0.3, "angle": -18.91 },
					{ "time": 0.4, "angle": -16.79 },
					{ "time": 0.5, "angle": 17.25 },
					{ "time": 0.6, "angle": 22.5 },
					{ "time": 0.64, "angle": 21.89 },
					{ "time": 0.8, "angle": -19.88 }
				],
				"translate": [
					{ "time": 0, "x": 0, "y": 0, "curve": "stepped" },
					{ "time": 0.8, "x": 0, "y": 0 }
				]
			},
			"leg_con_t": {
				"rotate": [
					{ "time": 0, "angle": 19.23 },
					{ "time": 0.1, "angle": -9.32 },
					{ "time": 0.2, "angle": -28.56 },
					{ "time": 0.3, "angle": 1.15 },
					{ "time": 0.4, "angle": 9.42 },
					{ "time": 0.5, "angle": -32 },
					{ "time": 0.6, "angle": -26.41 },
					{ "time": 0.64, "angle": -23.66 },
					{ "time": 0.7, "angle": -3.69 },
					{ "time": 0.8, "angle": 19.23 }
				],
				"translate": [
					{ "time": 0, "x": 0, "y": 0, "curve": "stepped" },
					{ "time": 0.8, "x": 0, "y": 0 }
				]
			},
			"leg_con_b": {
				"rotate": [
					{ "time": 0, "angle": 0.25 },
					{ "time": 0.1, "angle": -32.58 },
					{ "time": 0.2, "angle": -65.68 },
					{ "time": 0.3, "angle": -10.78 },
					{ "time": 0.5, "angle": -2.22 },
					{ "time": 0.6, "angle": 16.04 },
					{ "time": 0.7, "angle": 13.93 },
					{ "time": 0.8, "angle": -3.36 }
				],
				"translate": [
					{ "time": 0, "x": 0, "y": 0, "curve": "stepped" },
					{ "time": 0.8, "x": 0, "y": 0 }
				],
				"scale": [
					{ "time": 0, "x": 1.241, "y": 1 },
					{ "time": 0.2, "x": 1.607, "y": 1 },
					{ "time": 0.3, "x": 1.475, "y": 1 },
					{ "time": 0.6, "x": 1.315, "y": 1 }
				]
			},
			"leg_back": {
				"rotate": [
					{ "time": 0, "angle": 25.13 },
					{ "time": 0.1, "angle": 17.13 },
					{ "time": 0.2, "angle": 11.23 },
					{ "time": 0.4, "angle": -26.89 },
					{ "time": 0.5, "angle": -16.99 },
					{ "time": 0.6, "angle": 24.23 },
					{ "time": 0.7, "angle": 36.24 },
					{ "time": 0.8, "angle": 25.13 }
				],
				"translate": [
					{ "time": 0, "x": 0, "y": 0, "curve": "stepped" },
					{ "time": 0.8, "x": 0, "y": 0 }
				]
			},
			"leg_con_b2": {
				"rotate": [
					{ "time": 0, "angle": 7.21 },
					{ "time": 0.1, "angle": 12.02 },
					{ "time": 0.2, "angle": 18.3 },
					{ "time": 0.4, "angle": -0.79 },
					{ "time": 0.5, "angle": -32.66 },
					{ "time": 0.6, "angle": -61.61 },
					{ "time": 0.7, "angle": -4.47 },
					{ "time": 0.8, "angle": 7.21 }
				],
				"translate": [
					{ "time": 0, "x": 0, "y": 0, "curve": "stepped" },
					{ "time": 0.8, "x": 0, "y": 0 }
				],
				"scale": [
					{ "time": 0, "x": 1.192, "y": 1 },
					{ "time": 0.2, "x": 1.32, "y": 1 },
					{ "time": 0.6, "x": 1.666, "y": 1 },
					{ "time": 0.8, "x": 1.192, "y": 1 }
				]
			},
			"leg_con_t2": {
				"rotate": [
					{ "time": 0, "angle": 19.05 },
					{ "time": 0.1, "angle": -28.84 },
					{ "time": 0.2, "angle": -27.1 },
					{ "time": 0.3, "angle": -7.95 },
					{ "time": 0.4, "angle": 16.24 },
					{ "time": 0.5, "angle": -11.45 },
					{ "time": 0.6, "angle": -24.8 },
					{ "time": 0.7, "angle": 6.62 },
					{ "time": 0.8, "angle": 19.05 }
				],
				"translate": [
					{ "time": 0, "x": 0, "y": 0, "curve": "stepped" },
					{ "time": 0.8, "x": 0, "y": 0 }
				]
			},
			"leg_m_f2": {
				"rotate": [
					{ "time": 0, "angle": -15.77 },
					{ "time": 0.1, "angle": 23.92 },
					{ "time": 0.2, "angle": 23.43 },
					{ "time": 0.4, "angle": -14.3 },
					{ "time": 0.5, "angle": -18.05 },
					{ "time": 0.6, "angle": -47.56 },
					{ "time": 0.7, "angle": -20.52 },
					{ "time": 0.8, "angle": -15.77 }
				],
				"translate": [
					{ "time": 0, "x": 0, "y": 0, "curve": "stepped" },
					{ "time": 0.8, "x": 0, "y": 0 }
				]
			},
			"leg_b_f2": {
				"rotate": [
					{ "time": 0, "angle": -14.55 },
					{ "time": 0.1, "angle": -10.69 },
					{ "time": 0.2, "angle": -6.91 },
					{ "time": 0.3, "angle": 7.17 },
					{ "time": 0.4, "angle": 23.65 },
					{ "time": 0.5, "angle": 34.6 },
					{ "time": 0.7, "angle": -19.31 },
					{ "time": 0.8, "angle": -14.55 }
				],
				"translate": [
					{ "time": 0, "x": 0, "y": 0, "curve": "stepped" },
					{ "time": 0.8, "x": 0, "y": 0 }
				]
			},
			"torso_bottom": {
				"rotate": [
					{ "time": 0, "angle": 0 }
				],
				"translate": [
					{ "time": 0, "x": 0, "y": 0 }
				],
				"scale": [
					{
						"time": 0,
						"x": 1,
						"y": 1,
						"curve": [ 0.65, 0, 0.798, 0.78 ]
					},
					{
						"time": 0.4,
						"x": 1,
						"y": 0.751,
						"curve": [ 0.695, 0.01, 0.741, 0.85 ]
					},
					{ "time": 0.8, "x": 1, "y": 1 }
				]
			},
			"torso_top": {
				"rotate": [
					{
						"time": 0,
						"angle": -2.35,
						"curve": [ 0.385, 0.24, 0.71, 0.58 ]
					},
					{
						"time": 0.1,
						"angle": -0.95,
						"curve": [ 0.607, 0.01, 1, 0.61 ]
					},
					{
						"time": 0.3,
						"angle": -2.7,
						"curve": [ 0.388, 0, 0.716, 0.36 ]
					},
					{
						"time": 0.5,
						"angle": -0.95,
						"curve": [ 0.607, 0.01, 1, 0.61 ]
					},
					{
						"time": 0.7,
						"angle": -2.7,
						"curve": [ 0.447, 0, 0.754, 0.4 ]
					},
					{ "time": 0.8, "angle": -2.35 }
				],
				"translate": [
					{ "time": 0, "x": 9.15, "y": -61.22 },
					{
						"time": 0.1,
						"x": 6.42,
						"y": -112.71,
						"curve": [ 0.535, 0.01, 0.938, 0.66 ]
					},
					{ "time": 0.3, "x": 11.89, "y": -9.74 },
					{
						"time": 0.5,
						"x": 6.42,
						"y": -112.71,
						"curve": [ 0.535, 0.01, 0.938, 0.66 ]
					},
					{ "time": 0.7, "x": 11.89, "y": -9.74 },
					{ "time": 0.8, "x": 9.15, "y": -61.22 }
				],
				"scale": [
					{ "time": 0, "x": 1, "y": 0.886 },
					{ "time": 0.4, "x": 1, "y": 1 },
					{ "time": 0.8, "x": 1, "y": 0.886 }
				]
			},
			"head": {
				"rotate": [
					{ "time": 0, "angle": 0 }
				]
			},
			"torso front": {
				"scale": [
					{ "time": 0, "x": 1, "y": 0.907 },
					{ "time": 0.4, "x": 1, "y": 1 },
					{ "time": 0.8, "x": 1, "y": 0.907 }
				]
			},
			"arm_L": {
				"rotate": [
					{ "time": 0, "angle": 0 },
					{ "time": 0.4, "angle": -4.13 },
					{ "time": 0.8, "angle": 0 }
				],
				"scale": [
					{ "time": 0, "x": 1, "y": 1 },
					{ "time": 0.4, "x": 0.899, "y": 1 },
					{ "time": 0.8, "x": 1, "y": 1 }
				]
			},
			"arm right": {
				"scale": [
					{ "time": 0, "x": 1, "y": 1.049 },
					{ "time": 0.4, "x": 1, "y": 1 },
					{ "time": 0.8, "x": 1, "y": 1.049 }
				]
			}
		}
	}
}
}